groot/__init__.py
groot/functional.py
groot/node.py
groot/tree.py
groot/utils.py
i_am_groot-0.1.3.dist-info/LICENSE
i_am_groot-0.1.3.dist-info/METADATA
i_am_groot-0.1.3.dist-info/WHEEL
i_am_groot-0.1.3.dist-info/top_level.txt
i_am_groot-0.1.3.dist-info/RECORD
