Metadata-Version: 2.1
Name: i-am-groot
Version: 0.1.3
Summary: Manage hierarchical concept trees with style.
Home-page: https://chenchaozhao.github.io/groot/
Author: Chenchao Zhao
Author-email: chenchao.zhao@gmail.com
License: MIT
Platform: UNKNOWN
Requires-Dist: dataclasses
Requires-Dist: PyYaml
